{
  "settings": [
    {
      "id": "individualLocalIdentifier",
      "name": "Local Identifier",
      "description": "Plots the trajectory of the given individual local identifier. Leave empty for plotting all individuals in one plot",
      "defaultValue": null,
      "type": "STRING"
    },
    {
      "id": "myFiles",
      "name": "Upload Files",
      "description": "You can provide your own files. Expected file name is `my-machine.txt`",
      "defaultValue": null,
      "type": "LOCAL_FILE"
    }
  ],
  "providedAppFiles": [
    {
      "settingId": "myFiles",
      "from": "resources/local_app_files/provided-app-files/my_files"
    }
  ],
  "createsArtifacts": true,
  "license": {
    "key": "MIT"
  },
  "language": "eng",
  "keywords": [
    "example",
    "template"
  ],
  "people": [
    {
      "firstName": "Charles",
      "middleInitials": null,
      "lastName": "Darwin",
      "email": "creator@example.com",
      "roles": [
        "author",
        "creator"
      ],
      "orcid": null,
      "affiliation": null,
      "affiliationRor": null
    }
  ],
  "funding": [
    {
      "name": "funder name",
      "comment": "grant for App"
    }
  ],
  "references": [
    {
      "type": "IsDescribedBy",
      "note": "Darwin, C. 1900. The creation. Journal XY. 1-2",
      "url": "https://anylink.xyz"
    }
  ],
  "documentation": {
    "url": "https://github.com/yourAccount/my-app/README.md"
  }
}

